pyfaup/__init__.py
pyfaup/__version__.py
pyfaup/bind.py
pyfaup/faup.py
pyfaup/functions.py
pyfaup/mozilla.tlds
pyfaup/Darwin/x86_64/libfaupl.dylib
pyfaup/Linux/x86_64/libfaupl.so
pyfaup-1.2.dist-info/METADATA
pyfaup-1.2.dist-info/WHEEL
pyfaup-1.2.dist-info/top_level.txt
pyfaup-1.2.dist-info/RECORD
