Metadata-Version: 2.1
Name: pyfaup
Version: 1.2
Summary: Python bindings for the faup library
Home-page: https://www.github.com/stricaud/faup
Author: Sebastien Tricaud
Author-email: sebastien@honeynet.org
Maintainer: Sebastien Tricaud
Maintainer-email: sebastien@honeynet.org
License: MIT
Platform: UNKNOWN
